python_object_convert/__init__.py
python_object_convert/__version__.py
python_object_convert/obj_converter.py
python_object_convert-0.0.1.dist-info/METADATA
python_object_convert-0.0.1.dist-info/WHEEL
python_object_convert-0.0.1.dist-info/top_level.txt
python_object_convert-0.0.1.dist-info/RECORD
