Metadata-Version: 2.1
Name: python-object-convert
Version: 0.0.1
Summary: Convert python objects to camel case and snake case.
Home-page: https://github.com/iamfoysal/python_object_convert
Author: Mohammad Foysal
License: MIT
Project-URL: Source, https://github.com/iamfoysal/python_object_convert
Keywords: python,object,convert,camel,snake,case,keys,to,camel,case
Classifier: Development Status :: 4 - Beta
Classifier: Intended Audience :: Developers
Classifier: License :: OSI Approved :: BSD License
Classifier: Natural Language :: English
Classifier: Operating System :: OS Independent
Classifier: Programming Language :: Python
Classifier: Programming Language :: Python :: 3
Classifier: Programming Language :: Python :: 3.11
Classifier: Programming Language :: Python :: Implementation :: CPython
Classifier: Topic :: Software Development
Classifier: Topic :: Software Development :: Libraries :: Python Modules
Requires-Python: >=3.9
Requires-Dist: requests
